gravityfalls/__init__.py
gravity_falls-0.0.2.dist-info/LICENSE
gravity_falls-0.0.2.dist-info/METADATA
gravity_falls-0.0.2.dist-info/WHEEL
gravity_falls-0.0.2.dist-info/top_level.txt
gravity_falls-0.0.2.dist-info/RECORD
