Metadata-Version: 2.1
Name: gravity-falls
Version: 0.0.2
Summary: Implementation of famous ancient ciphers and encryption techniques
Home-page: https://github.com/er-knight/gravityfalls
Author: er-knight (Ajay Dandge)
Author-email: menobleknight@gmail.com
License: UNKNOWN
Project-URL: Bug Tracker, https://github.com/er-knight/gravityfalls/issues
Platform: UNKNOWN
Classifier: Programming Language :: Python :: 3
Classifier: License :: OSI Approved :: GNU General Public License v3 (GPLv3)
Classifier: Operating System :: OS Independent
Requires-Python: >=3.6
License-File: LICENSE
